{
    "files": [
        {
            "name": "26_0_r0_151/flashplayer26_0r0_151_linux.i386.tar.gz",
            "offset": 58,
            "size": 8492462
        },
        {
            "name": "26_0_r0_151/flashplayer26_0r0_151_linux.x86_64.tar.gz",
            "offset": 8365559,
            "size": 9002831
        },
        {
            "name": "26_0_r0_151/flashplayer26_0r0_151_linux_sa.x86_64.tar.gz",
            "offset": 17211775,
            "size": 8466789
        },
        {
            "name": "26_0_r0_151/flashplayer26_0r0_151_linuxpep.i386.tar.gz",
            "offset": 25645149,
            "size": 8536460
        },
        {
            "name": "26_0_r0_151/flashplayer26_0r0_151_linuxpep.x86_64.tar.gz",
            "offset": 34072440,
            "size": 9449331
        },
        {
            "name": "26_0_r0_151/flashplayer26_0r0_151_mac.dmg",
            "offset": 43367483,
            "size": 19176693
        },
        {
            "name": "26_0_r0_151/flashplayer26_0r0_151_mac_pkg.dmg",
            "offset": 62537288,
            "size": 18640584
        },
        {
            "name": "26_0_r0_151/flashplayer26_0r0_151_mac_sa.dmg",
            "offset": 81046173,
            "size": 17078406
        },
        {
            "name": "26_0_r0_151/flashplayer26_0r0_151_macpep.dmg",
            "offset": 98109800,
            "size": 18649408
        },
        {
            "name": "26_0_r0_151/flashplayer26_0r0_151_macpep_pkg.dmg",
            "offset": 116752393,
            "size": 18120399
        },
        {
            "name": "26_0_r0_151/flashplayer26_0r0_151_win.exe",
            "offset": 134740693,
            "size": 20648960
        },
        {
            "name": "26_0_r0_151/flashplayer26_0r0_151_win.msi",
            "offset": 154942496,
            "size": 21816832
        },
        {
            "name": "26_0_r0_151/flashplayer26_0r0_151_win_sa.exe",
            "offset": 175507172,
            "size": 15952896
        },
        {
            "name": "26_0_r0_151/flashplayer26_0r0_151_winax.exe",
            "offset": 182179246,
            "size": 20118528
        },
        {
            "name": "26_0_r0_151/flashplayer26_0r0_151_winax.msi",
            "offset": 201850655,
            "size": 21282304
        },
        {
            "name": "26_0_r0_151/flashplayer26_0r0_151_winpep.exe",
            "offset": 221882355,
            "size": 20616704
        },
        {
            "name": "26_0_r0_151/flashplayer26_0r0_151_winpep.msi",
            "offset": 242051968,
            "size": 21780480
        },
        {
            "name": "26_0_r0_151/uninstall_flashplayer26_0r0_151_mac.dmg",
            "offset": 262579577,
            "size": 429437
        },
        {
            "name": "26_0_r0_151/uninstall_flashplayer26_0r0_151_win.exe",
            "offset": 263000659,
            "size": 1281536
        },
        {
            "name": "26_0_r0_151_debug/flashplayer26_0r0_151_linux_debug.i386.tar.gz",
            "offset": 263829630,
            "size": 8806562
        },
        {
            "name": "26_0_r0_151_debug/flashplayer26_0r0_151_linux_debug.x86_64.tar.gz",
            "offset": 272494455,
            "size": 9368243
        },
        {
            "name": "26_0_r0_151_debug/flashplayer26_0r0_151_linux_sa_debug.x86_64.tar.gz",
            "offset": 281690033,
            "size": 8779435
        },
        {
            "name": "26_0_r0_151_debug/flashplayer26_0r0_151_linuxpep_debug.x86_64.tar.gz",
            "offset": 290434125,
            "size": 9883169
        },
        {
            "name": "26_0_r0_151_debug/flashplayer26_0r0_151_mac_debug.dmg",
            "offset": 300148115,
            "size": 19406198
        },
        {
            "name": "26_0_r0_151_debug/flashplayer26_0r0_151_mac_sa_debug.dmg",
            "offset": 319546851,
            "size": 17514527
        },
        {
            "name": "26_0_r0_151_debug/flashplayer26_0r0_151_macpep_debug.dmg",
            "offset": 337046031,
            "size": 18957842
        },
        {
            "name": "26_0_r0_151_debug/flashplayer26_0r0_151_win_debug.exe",
            "offset": 355997203,
            "size": 20432896
        },
        {
            "name": "26_0_r0_151_debug/flashplayer26_0r0_151_win_sa_debug.exe",
            "offset": 375983164,
            "size": 16780288
        },
        {
            "name": "26_0_r0_151_debug/flashplayer26_0r0_151_winax_debug.exe",
            "offset": 382944547,
            "size": 20482048
        },
        {
            "name": "26_0_r0_151_debug/flashplayer26_0r0_151_winpep_debug.exe",
            "offset": 402979427,
            "size": 21085184
        }
    ],
    "modified": "Tue, 12 Sep 2017 03:50:46 GMT",
    "size": 423621380,
    "url": "http://web.archive.org/web/20190403202921id_/https://fpdownload.macromedia.com/pub/flashplayer/installers/archive/fp_26.0.0.151_archive.zip"
}
